{"academic painting":"아카데믹한 명화","amazing painting":"대단한 명화","ancient statue":"태고의 조각","basic painting":"용감한 명화","beautiful statue":"아름다운 조각","calm painting":"평온한 명화","common painting":"평범한 명화","detailed painting":"섬세한 명화","dynamic painting":"멋들어진 명화","familiar statue":"익숙한 조각","famous painting":"유명한 명화","flowery painting":"진귀한 명화","gallant statue":"늠름한 조각","glowing painting":"빛의 명화","graceful painting":"절제된 명화","great statue":"위대한 조각","informative statue":"단서가 되는 조각","jolly painting":"재미있는 명화","moody painting":"힘찬 명화","motherly statue":"모성이 느껴지는 조각","moving painting":"예쁜 명화","mysterious painting":"미스터리한 명화","mystic statue":"신비로운 조각","nice painting":"좋은 명화","perfect painting":"훌륭한 명화","proper painting":"활기 넘치는 명화","quaint painting":"침착한 명화","robust statue":"듬직한 조각","rock-head statue":"돌 머리의 조각","scary painting":"씩씩한 명화","scenic painting":"뛰어난 명화","serene painting":"아늑한 명화","sinking painting":"가라앉는 명화","solemn painting":"엄숙한 명화","tremendous statue":"어마어마한 조각","twinkling painting":"반짝이는 명화","valiant statue":"거룩한 조각","warm painting":"느낌이 좋은 명화","warrior statue":"무사의 조각","wild painting left half":"혼란스러운 명화의 왼쪽","wild painting right half":"혼란스러운 명화의 오른쪽","wistful painting":"근사한 명화","worthy painting":"가치 있는 명화"}